bionic/__init__.py
bionic/cache_api.py
bionic/code_hasher.py
bionic/code_references.py
bionic/dagviz.py
bionic/datatypes.py
bionic/decoration.py
bionic/decorators.py
bionic/deriver.py
bionic/exception.py
bionic/executor.py
bionic/filecopier.py
bionic/flow.py
bionic/gcs.py
bionic/interpret.py
bionic/persistence.py
bionic/protocol.py
bionic/protocols.py
bionic/provider.py
bionic/tokenization.py
bionic/util.py
bionic/aip/__init__.py
bionic/aip/client.py
bionic/aip/docker_image_builder.py
bionic/aip/main.py
bionic/aip/state.py
bionic/aip/task.py
bionic/core/__init__.py
bionic/core/flow_execution.py
bionic/core/task_execution.py
bionic/deps/__init__.py
bionic/deps/extras.py
bionic/deps/optdep.py
bionic/descriptors/__init__.py
bionic/descriptors/ast.py
bionic/descriptors/parsing.py
bionic/flake8/__init__.py
bionic/flake8/check_dnode_match.py
bionic/utils/__init__.py
bionic/utils/files.py
bionic/utils/gcp_auth.py
bionic/utils/keyed_priority_stack.py
bionic/utils/misc.py
bionic/utils/reload.py
bionic/utils/urls.py
example/__init__.py
example/basic_workflow.py
example/hello_world.py
example/intro_workflow.py
example/ml_workflow.py
example/ml_workflow_cli.py
tests/__init__.py
tests/conftest.py
tests/helpers.py
tests/test_code_hasher.py
tests/test_code_references.py
tests/test_descriptors.py
tests/test_helpers.py
tests/test_optdep.py
tests/test_tokenize.py
tests/test_flow/__init__.py
tests/test_flow/conftest.py
tests/test_flow/fakes.py
tests/test_flow/generate_test_compatibility_cache.py
tests/test_flow/test_api.py
tests/test_flow/test_cache_api.py
tests/test_flow/test_copy.py
tests/test_flow/test_dagviz.py
tests/test_flow/test_execution.py
tests/test_flow/test_executor.py
tests/test_flow/test_gather.py
tests/test_flow/test_interactions.py
tests/test_flow/test_join.py
tests/test_flow/test_logging.py
tests/test_flow/test_merge.py
tests/test_flow/test_multi_out.py
tests/test_flow/test_new_api.py
tests/test_flow/test_outputs.py
tests/test_flow/test_persistence.py
bionic-0.11.1.dist-info/LICENSE.txt
bionic-0.11.1.dist-info/METADATA
bionic-0.11.1.dist-info/WHEEL
bionic-0.11.1.dist-info/top_level.txt
bionic-0.11.1.dist-info/RECORD
