Metadata-Version: 2.1
Name: bionic
Version: 0.11.1
Summary: A Python framework for building, running, and sharing data science workflows
Home-page: https://github.com/square/bionic
Author: Janek Klawe
Author-email: janek@squareup.com
License: Apache License 2.0
Keywords: bionic
Platform: UNKNOWN
Classifier: Development Status :: 3 - Alpha
Classifier: Intended Audience :: Developers
Classifier: Natural Language :: English
Classifier: License :: OSI Approved :: Apache Software License
Classifier: Programming Language :: Python :: 3
Classifier: Programming Language :: Python :: 3.7
Requires-Python: >=3.7
Requires-Dist: attrs (>=20.1)
Requires-Dist: cattrs
Requires-Dist: PyYAML
Requires-Dist: numpy
Requires-Dist: pandas
Requires-Dist: pyarrow
Requires-Dist: pyrsistent (!=0.19.1)
Requires-Dist: decorator (<5)
Provides-Extra: aip
Requires-Dist: cloudpickle ; extra == 'aip'
Requires-Dist: docker ; extra == 'aip'
Requires-Dist: fsspec ; extra == 'aip'
Requires-Dist: gcsfs ; extra == 'aip'
Requires-Dist: google-api-python-client ; extra == 'aip'
Requires-Dist: google-auth ; extra == 'aip'
Requires-Dist: google-cloud-logging ; extra == 'aip'
Provides-Extra: dask
Requires-Dist: dask[dataframe] ; extra == 'dask'
Provides-Extra: dev
Requires-Dist: GitPython ; extra == 'dev'
Requires-Dist: Pillow ; extra == 'dev'
Requires-Dist: black ; extra == 'dev'
Requires-Dist: bumpversion ; extra == 'dev'
Requires-Dist: cloudpickle ; extra == 'dev'
Requires-Dist: dask[dataframe] ; extra == 'dev'
Requires-Dist: dill ; extra == 'dev'
Requires-Dist: docker ; extra == 'dev'
Requires-Dist: flake8 ; extra == 'dev'
Requires-Dist: flake8-fixme ; extra == 'dev'
Requires-Dist: flake8-print ; extra == 'dev'
Requires-Dist: fsspec ; extra == 'dev'
Requires-Dist: gcsfs ; extra == 'dev'
Requires-Dist: geopandas ; extra == 'dev'
Requires-Dist: google-api-python-client ; extra == 'dev'
Requires-Dist: google-auth ; extra == 'dev'
Requires-Dist: google-cloud-logging ; extra == 'dev'
Requires-Dist: hsluv ; extra == 'dev'
Requires-Dist: importlib-metadata (<5) ; extra == 'dev'
Requires-Dist: jupyter ; extra == 'dev'
Requires-Dist: loky ; extra == 'dev'
Requires-Dist: matplotlib (!=3.2.*,>=3.1) ; extra == 'dev'
Requires-Dist: nbsphinx ; extra == 'dev'
Requires-Dist: networkx ; extra == 'dev'
Requires-Dist: pydot ; extra == 'dev'
Requires-Dist: pytest ; extra == 'dev'
Requires-Dist: pytest-shard ; extra == 'dev'
Requires-Dist: scikit-learn ; extra == 'dev'
Requires-Dist: sphinx (!=3.2.0) ; extra == 'dev'
Requires-Dist: sphinx-autobuild ; extra == 'dev'
Requires-Dist: sphinx-rtd-theme ; extra == 'dev'
Provides-Extra: dill
Requires-Dist: dill ; extra == 'dill'
Provides-Extra: examples
Requires-Dist: Pillow ; extra == 'examples'
Requires-Dist: hsluv ; extra == 'examples'
Requires-Dist: matplotlib (!=3.2.*,>=3.1) ; extra == 'examples'
Requires-Dist: networkx ; extra == 'examples'
Requires-Dist: pydot ; extra == 'examples'
Requires-Dist: scikit-learn ; extra == 'examples'
Provides-Extra: full
Requires-Dist: Pillow ; extra == 'full'
Requires-Dist: cloudpickle ; extra == 'full'
Requires-Dist: dask[dataframe] ; extra == 'full'
Requires-Dist: dill ; extra == 'full'
Requires-Dist: docker ; extra == 'full'
Requires-Dist: fsspec ; extra == 'full'
Requires-Dist: gcsfs ; extra == 'full'
Requires-Dist: geopandas ; extra == 'full'
Requires-Dist: google-api-python-client ; extra == 'full'
Requires-Dist: google-auth ; extra == 'full'
Requires-Dist: google-cloud-logging ; extra == 'full'
Requires-Dist: hsluv ; extra == 'full'
Requires-Dist: loky ; extra == 'full'
Requires-Dist: matplotlib (!=3.2.*,>=3.1) ; extra == 'full'
Requires-Dist: networkx ; extra == 'full'
Requires-Dist: pydot ; extra == 'full'
Requires-Dist: scikit-learn ; extra == 'full'
Provides-Extra: gcp
Requires-Dist: fsspec ; extra == 'gcp'
Requires-Dist: gcsfs ; extra == 'gcp'
Provides-Extra: geopandas
Requires-Dist: geopandas ; extra == 'geopandas'
Provides-Extra: image
Requires-Dist: Pillow ; extra == 'image'
Provides-Extra: matplotlib
Requires-Dist: Pillow ; extra == 'matplotlib'
Requires-Dist: matplotlib (!=3.2.*,>=3.1) ; extra == 'matplotlib'
Provides-Extra: parallel
Requires-Dist: cloudpickle ; extra == 'parallel'
Requires-Dist: loky ; extra == 'parallel'
Provides-Extra: standard
Requires-Dist: Pillow ; extra == 'standard'
Requires-Dist: hsluv ; extra == 'standard'
Requires-Dist: matplotlib (!=3.2.*,>=3.1) ; extra == 'standard'
Requires-Dist: networkx ; extra == 'standard'
Requires-Dist: pydot ; extra == 'standard'
Provides-Extra: viz
Requires-Dist: Pillow ; extra == 'viz'
Requires-Dist: hsluv ; extra == 'viz'
Requires-Dist: networkx ; extra == 'viz'
Requires-Dist: pydot ; extra == 'viz'
